MANIFEST.in
README.rst
setup.cfg
setup.py
samsa/__init__.py
samsa/brokers.py
samsa/client.py
samsa/cluster.py
samsa/exceptions.py
samsa/handlers.py
samsa/partitioners.py
samsa/partitions.py
samsa/topics.py
samsa.egg-info/PKG-INFO
samsa.egg-info/SOURCES.txt
samsa.egg-info/dependency_links.txt
samsa.egg-info/not-zip-safe
samsa.egg-info/requires.txt
samsa.egg-info/top_level.txt
samsa/consumer/__init__.py
samsa/consumer/consumer.py
samsa/consumer/partitions.py
samsa/contrib/__init__.py
samsa/contrib/handler.py
samsa/test/__init__.py
samsa/test/case.py
samsa/test/integration.py
samsa/test/kafka-run-class.sh
samsa/utils/__init__.py
samsa/utils/delayedconfig.py
samsa/utils/functional.py
samsa/utils/log.py
samsa/utils/namedstruct.py
samsa/utils/socket.py
samsa/utils/structuredio.py