Metadata-Version: 1.0
Name: samsa
Version: 0.3.11
Summary: Featureful Kafka client.
Home-page: https://github.com/getsamsa/samsa
Author: Ted Kaemming, Matthew Hooker, and Keith Bourgoin
Author-email: samsa-users@googlegroups.com
License: Apache License 2.0
Platform: UNKNOWN
